README.rst
setup.cfg
setup.py
facebook_py_sdk.egg-info/PKG-INFO
facebook_py_sdk.egg-info/SOURCES.txt
facebook_py_sdk.egg-info/dependency_links.txt
facebook_py_sdk.egg-info/requires.txt
facebook_py_sdk.egg-info/top_level.txt
facebook_sdk/__init__.py
facebook_sdk/authentication.py
facebook_sdk/client.py
facebook_sdk/constants.py
facebook_sdk/exceptions.py
facebook_sdk/facebook.py
facebook_sdk/facebook_file.py
facebook_sdk/py.typed
facebook_sdk/request.py
facebook_sdk/response.py
facebook_sdk/utils.py
facebook_sdk/version.py