Metadata-Version: 2.1
Name: facebook-py-sdk
Version: 1.2.1
Summary: Facebook Python SDK
Home-page: https://github.com/eventbrite/facebook-py-sdk
Author: Zeta Hernandez
Author-email: zetahernandez@gmail.com
License: MIT
Platform: UNKNOWN
Classifier: License :: OSI Approved :: MIT License
Classifier: Programming Language :: Python
Classifier: Programming Language :: Python :: 2.7
Classifier: Programming Language :: Python :: 3.4
Classifier: Programming Language :: Python :: 3.5
Classifier: Programming Language :: Python :: 3.6
Classifier: Programming Language :: Python :: 3.7
Provides-Extra: testing
